<?xml version="1.0" encoding="UTF-8"?>
<termsRecord xmlns="http://www.vocabs.dlese" xmlns:xsi="http://www.w3.org/2001/XMLSchema-instance" xsi:schemaLocation="http://www.vocabs.dlese
http://www.dlese.org/Metadata/vocabularies/management/collection/policy.xsd">
	<field name="policy" id="" language="en-us">
		<definition system="meta" interface="default">Different policies that collections may use</definition>
		<definition system="dcs" interface="default"></definition>
		<definition system="dds" interface="default"></definition>

		<value vocab="Agreement to DLESE intellectual property" id="">
			<definition system="meta" interface="default">Indicates whether or not the collection aligns with DLESE's Intellectual Property policy</definition>
			<definition system="dcs" interface="default"></definition>
			<definition system="dds" interface="default"></definition>
		</value>

		<value vocab="Agreement to redistribution of metadata" id="">
			<definition system="meta" interface="default">Indicates whether a collection's metadata may be redistributed upon harvest</definition>
			<definition system="dcs" interface="default"></definition>
			<definition system="dds" interface="default"></definition>
		</value>

		<value vocab="Collection persistence plan" id="">
			<definition system="meta" interface="default">Describes how the collection is expected to persist over a long period of time, greater than five years</definition>
			<definition system="dcs" interface="default"></definition>
			<definition system="dds" interface="default"></definition>
		</value>

		<value vocab="Collection scope" id="">
			<definition system="meta" interface="default">Describes the purpose of a collection and may include other information about selection criteria, terms of use and persistence</definition>
			<definition system="dcs" interface="default"></definition>
			<definition system="dds" interface="default"></definition>
		</value>

		<value vocab="Intellectual property of metadata" id="">
			<definition system="meta" interface="default">Indicates copyright information about the metadata records of a collection</definition>
			<definition system="dcs" interface="default"></definition>
			<definition system="dds" interface="default"></definition>
		</value>

		<value vocab="Intellectual property of resources" id="">
			<definition system="meta" interface="default">Indicates intellectual property information about a collection's resources</definition>
			<definition system="dcs" interface="default"></definition>
			<definition system="dds" interface="default"></definition>
		</value>

		<value vocab="Other" id="">
			<definition system="meta" interface="default">Other information, not described by the other policies listed, is provided about a collection</definition>
			<definition system="dcs" interface="default"></definition>
			<definition system="dds" interface="default"></definition>
		</value>

		<value vocab="Quality assurance of metadata" id="">
			<definition system="meta" interface="default">Describes the mechanisms a collections uses to ensure high-quality metadata</definition>
			<definition system="dcs" interface="default"></definition>
			<definition system="dds" interface="default"></definition>
		</value>

		<value vocab="Quality assurance of resources" id="">
			<definition system="meta" interface="default">Describes the mechanisms a collection uses to ensure high-quality resources particularly resources directly developed by collection builders</definition>
			<definition system="dcs" interface="default"></definition>
			<definition system="dds" interface="default"></definition>
		</value>

		<value vocab="Review or selection of resources" id="">
			<definition system="meta" interface="default">Describes the mechanisms used to select resources, both direct collection builder developed resources and arbitrarily cataloged resources, for a collection</definition>
			<definition system="dcs" interface="default"></definition>
			<definition system="dds" interface="default"></definition>
		</value>

		<value vocab="Terms of use for metadata" id="">
			<definition system="meta" interface="default">Describes the terms of use for the metadata generated by a collection</definition>
			<definition system="dcs" interface="default"></definition>
			<definition system="dds" interface="default"></definition>
		</value>

		<value vocab="Terms of use for resources" id="">
			<definition system="meta" interface="default">Describes the terms of use of the resources for the collection</definition>
			<definition system="dcs" interface="default"></definition>
			<definition system="dds" interface="default"></definition>
		</value>

	</field>
</termsRecord>
<!--	*** LICENSE INFORMATION *****
		Copyright 2002, 2003 DLESE Program Center
		University Corporation for Atmospheric Research (UCAR)
		P.O. Box 3000, Boulder, CO 80307, United States of America
		email: support@dlese.org. 
These XML instance documents are free software; you can redistribute them and/or modify them under the terms of the GNU General Public License as published by the Free Software Foundation; either version 2 of the License, or (at your option) any later version.  These XML instance documents are distributed in the hope that they will be useful, but WITHOUT ANY WARRANTY; without even the implied warranty of MERCHANTABILITY or FITNESS FOR A PARTICULAR PURPOSE. See the GNU General Public License for more details. You should have received a copy of the GNU General Public License along with this project; if not, write to the Free Software Foundation, Inc., 59 Temple Place, Suite 330, Boston, MA 02111-1307 USA -->
